{
  "name": "attendStatus",
  "title": "打卡记录",
  "fields": {
    "asid": {
      "name": "asid",
      "title": "打卡状态id",
      "identity": true,
      "increment": true,
      "unique": false,
      "column": "asid",
      "type": "integer"
    },
    "empid": {
      "name": "empid",
      "title": "员工id",
      "required": false,
      "identity": false,
      "increment": false,
      "unique": false,
      "column": "emp_id",
      "type": "integer",
      "length": 200,
      "precision": 0,
      "scale": 0,
      "columnNull": false
    },
    "taskid": {
      "name": "taskid",
      "title": "任务id",
      "required": true,
      "identity": false,
      "increment": false,
      "unique": false,
      "column": "task_id",
      "type": "integer",
      "length": 200,
      "precision": 0,
      "scale": 0,
      "columnNull": false
    },
    "status": {
      "name": "status",
      "title": "打卡状态",
      "required": true,
      "identity": false,
      "increment": false,
      "unique": false,
      "column": "status",
      "type": "integer",
      "length": 1,
      "precision": 0,
      "scale": 0,
      "columnNull": false
    },
    "createTime": {
      "name": "createTime",
      "title": "创建时间",
      "required": true,
      "identity": false,
      "increment": false,
      "unique": false,
      "column": "create_time",
      "type": "timestamp",
      "length": 0,
      "precision": 0,
      "scale": 0,
      "columnDefault": "CURRENT_TIMESTAMP",
      "columnNull": false
    },
    "deleted": {
      "name": "deleted",
      "title": "删除标记位",
      "required": true,
      "identity": false,
      "increment": false,
      "unique": false,
      "column": "deleted",
      "type": "integer",
      "length": 1,
      "precision": 0,
      "scale": 0,
      "default": 0,
      "columnNull": false
    }
  },
  "relations": {},
  "filters": {},
  "protocols": {},
  "onEvents": {},
  "queries": {},
  "creates": {},
  "updates": {},
  "deletes": {},
  "finds": {},
  "groupBys": {},
  "selects": {},
  "orderBys": {},
  "aggregates": {},
  "queryExprs": {
    "selects": {},
    "orderBys": {},
    "groupBys": {},
    "aggregates": {},
    "filters": {}
  },
  "generates": "create, update, delete, find, query",
  "logicalDeletes": {}
}